{
  "date": "2026-05-17",
  "generated_at": "2026-05-17T17:35:35.541542+09:00",
  "summary": {
    "total_reviewed": 14,
    "fit": 2,
    "review": 10,
    "excluded": 2
  },
  "fit": [
    {
      "no": "R26BK01521716",
      "title": "2026학년도 오주중학교 3학년 소규모테마형교육여행  위탁용역",
      "org": "서울특별시강동교육청 오주중학교",
      "deadline": "20260529",
      "amount": 68354818,
      "amount_label": "6,835만원",
      "urgent": false,
      "tags": [
        "교육·문화"
      ],
      "url": "https://www.g2b.go.kr/link/PNPE027_01/single/?bidPbancNo=R26BK01521716&bidPbancOrd=000",
      "status": "fit"
    },
    {
      "no": "R26BK01527139",
      "title": "2026년 국립공주박물관 특별전 계룡산 디지털콘텐츠 제작 및 설치 용역",
      "org": "문화체육관광부 국립중앙박물관 공주박물관",
      "deadline": "20260529",
      "amount": 181818182,
      "amount_label": "1억 8,181만원",
      "urgent": false,
      "tags": [
        "콘텐츠 제작"
      ],
      "url": "https://www.g2b.go.kr/link/PNPE027_01/single/?bidPbancNo=R26BK01527139&bidPbancOrd=000",
      "status": "fit"
    }
  ],
  "review": [
    {
      "no": "R26BK01527070",
      "title": "2026년 은평소방서 보이는 소화기 유지관리 용역",
      "org": "서울특별시 은평소방서",
      "deadline": "20260518",
      "amount": 12520000,
      "amount_label": "1,252만원",
      "urgent": true,
      "tags": [
        "기타"
      ],
      "url": "https://www.g2b.go.kr/link/PNPE027_01/single/?bidPbancNo=R26BK01527070&bidPbancOrd=000",
      "status": "review"
    },
    {
      "no": "R26BK01527102",
      "title": "2026년 농어촌 빈집정비사업 및 슬레이트처리사업(서부) 폐기물처리용역",
      "org": "충청남도 서산시",
      "deadline": "20260522",
      "amount": 70390909,
      "amount_label": "7,039만원",
      "urgent": false,
      "tags": [
        "기타"
      ],
      "url": "https://www.g2b.go.kr/link/PNPE027_01/single/?bidPbancNo=R26BK01527102&bidPbancOrd=000",
      "status": "review"
    },
    {
      "no": "R26BK01527105",
      "title": "2026년 농어촌 빈집정비사업 및 슬레이트처리사업(북부) 폐기물처리용역",
      "org": "충청남도 서산시",
      "deadline": "20260522",
      "amount": 88000000,
      "amount_label": "8,800만원",
      "urgent": false,
      "tags": [
        "기타"
      ],
      "url": "https://www.g2b.go.kr/link/PNPE027_01/single/?bidPbancNo=R26BK01527105&bidPbancOrd=000",
      "status": "review"
    },
    {
      "no": "R26BK01527107",
      "title": "2026년 농어촌 빈집정비사업 및 슬레이트처리사업(동부) 폐기물처리용역",
      "org": "충청남도 서산시",
      "deadline": "20260522",
      "amount": 59809091,
      "amount_label": "5,980만원",
      "urgent": false,
      "tags": [
        "기타"
      ],
      "url": "https://www.g2b.go.kr/link/PNPE027_01/single/?bidPbancNo=R26BK01527107&bidPbancOrd=000",
      "status": "review"
    },
    {
      "no": "R26BK01527108",
      "title": "2026년 농어촌 빈집정비사업 및 슬레이트처리사업(남부) 폐기물처리용역",
      "org": "충청남도 서산시",
      "deadline": "20260522",
      "amount": 59536364,
      "amount_label": "5,953만원",
      "urgent": false,
      "tags": [
        "기타"
      ],
      "url": "https://www.g2b.go.kr/link/PNPE027_01/single/?bidPbancNo=R26BK01527108&bidPbancOrd=000",
      "status": "review"
    },
    {
      "no": "R26BK01527109",
      "title": "2026년 도심지 빈집정비사업 및 슬레이트처리사업(동부) 폐기물처리용역",
      "org": "충청남도 서산시",
      "deadline": "20260522",
      "amount": 47645455,
      "amount_label": "4,764만원",
      "urgent": false,
      "tags": [
        "기타"
      ],
      "url": "https://www.g2b.go.kr/link/PNPE027_01/single/?bidPbancNo=R26BK01527109&bidPbancOrd=000",
      "status": "review"
    },
    {
      "no": "R26BK01527111",
      "title": "2026년 도심지 빈집정비사업 및 슬레이트처리사업(서부) 폐기물처리용역",
      "org": "충청남도 서산시",
      "deadline": "20260522",
      "amount": 60818182,
      "amount_label": "6,081만원",
      "urgent": false,
      "tags": [
        "기타"
      ],
      "url": "https://www.g2b.go.kr/link/PNPE027_01/single/?bidPbancNo=R26BK01527111&bidPbancOrd=000",
      "status": "review"
    },
    {
      "no": "R26BK01527114",
      "title": "2026년 소규모 빈집철거지원사업 및 슬레이트처리사업 폐기물처리용역",
      "org": "충청남도 서산시",
      "deadline": "20260522",
      "amount": 41436364,
      "amount_label": "4,143만원",
      "urgent": false,
      "tags": [
        "기타"
      ],
      "url": "https://www.g2b.go.kr/link/PNPE027_01/single/?bidPbancNo=R26BK01527114&bidPbancOrd=000",
      "status": "review"
    },
    {
      "no": "R26BK01525563",
      "title": "2026학년도 오주중학교 2학년 수련활동  용역업체선정 ",
      "org": "서울특별시강동교육청 오주중학교",
      "deadline": "20260529",
      "amount": 37219091,
      "amount_label": "3,721만원",
      "urgent": false,
      "tags": [
        "기타"
      ],
      "url": "https://www.g2b.go.kr/link/PNPE027_01/single/?bidPbancNo=R26BK01525563&bidPbancOrd=000",
      "status": "review"
    },
    {
      "no": "R26BK01527153",
      "title": "진해신항 에너지 인프라 구축방안 수립용역",
      "org": "부산항만공사",
      "deadline": "20260528",
      "amount": 100000000,
      "amount_label": "1억원",
      "urgent": false,
      "tags": [
        "기타"
      ],
      "url": "https://www.g2b.go.kr/link/PNPE027_01/single/?bidPbancNo=R26BK01527153&bidPbancOrd=000",
      "status": "review"
    }
  ]
}